dtw_python-1.7.2.dist-info/RECORD
dtw_python-1.7.2.dist-info/WHEEL
dtw_python-1.7.2.dist-info/entry_points.txt
dtw_python-1.7.2.dist-info/top_level.txt
dtw_python-1.7.2.dist-info/METADATA
dtw_python-1.7.2.dist-info/licenses/COPYING
dtw_python-1.7.2.dist-info/licenses/AUTHORS.rst
maintainer/roxypick.py
tests/query.csv
tests/test_doctests.py
tests/test_issues.py
tests/test_cran.py
tests/test_dtw.py
tests/reference.csv
tests/test_cli.py
tests/test_countPaths.py
tests/test_dtw_s.py
docs/conf.py
dtw/dtw_core.c
dtw/_dtw_utils.cpython-39-darwin.so
dtw/warpArea.py
dtw/window.py
dtw/countPaths.py
dtw/_dtw_utils.c
dtw/_globalCostMatrix.py
dtw/__init__.py
dtw/dtwPlot.py
dtw/stepPattern.py
dtw/_dtw_utils.pyx
dtw/dtw_core.h
dtw/mvm.py
dtw/dtw_test_data.py
dtw/warp.py
dtw/dtw.py
dtw/__main__.py
dtw/_backtrack.py
dtw/data/aami3b.csv
dtw/data/aami3a.csv
