Metadata-Version: 2.4
Name: dtw-python
Version: 1.7.2
Summary: A comprehensive implementation of dynamic time warping (DTW) algorithms.
Home-page: https://DynamicTimeWarping.github.io
Author-email: Toni Giorgino <toni.giorgino@gmail.com>
License-Expression: GPL-3.0-or-later
Project-URL: Homepage, https://dynamictimewarping.github.io/
Project-URL: Repository, https://github.com/DynamicTimeWarping/dtw-python
Project-URL: Documentation, https://dynamictimewarping.github.io/python/
Keywords: timeseries,alignment
Classifier: Development Status :: 5 - Production/Stable
Classifier: Intended Audience :: Science/Research
Classifier: Topic :: Scientific/Engineering
Classifier: Natural Language :: English
Classifier: Programming Language :: Python :: 3
Classifier: Programming Language :: Python :: 3.9
Classifier: Programming Language :: Python :: 3.10
Classifier: Programming Language :: Python :: 3.11
Classifier: Programming Language :: Python :: 3.12
Classifier: Programming Language :: Python :: 3.13
Requires-Python: >=3.9
License-File: COPYING
License-File: AUTHORS.rst
Requires-Dist: numpy>=2.0
Requires-Dist: scipy
Provides-Extra: test
Requires-Dist: numpy; extra == "test"
Dynamic: home-page
Dynamic: license-file
